{
    "txn_type": "subscr_cancel",
    "subscr_id": "I-HS7G3B8HX8WG",
    "last_name": "buyer",
    "residence_country": "US",
    "mc_currency": "USD",
    "item_name": "Acquaintance",
    "business": "jesse@updog.co",
    "amount3": "1.99",
    "recurring": "1",
    "verify_sign": "AS54rPUCw9wOTuVl0m1aSg09HaI8ABjxnZxyywHW3DHA5QXhqxbamFYV",
    "payer_status": "verified",
    "test_ipn": "1",
    "payer_email": "jesse-buyer@updog.co",
    "first_name": "test",
    "receiver_email": "jesse@updog.co",
    "payer_id": "6J42DMGGV2LGW",
    "reattempt": "1",
    "subscr_date": "07:10:22 Mar 28, 2017 PDT",
    "custom": "1",
    "charset": "windows-1252",
    "notify_version": "3.8",
    "period3": "1 M",
    "mc_amount3": "1.99",
    "ipn_track_id": "4281efdd9d7b8",
    "controller": "subscriptions",
    "action": "create"
}
